zelphi/__init__.py
zelphi/cli.py
zelphi-0.1.0.dist-info/METADATA
zelphi-0.1.0.dist-info/WHEEL
zelphi-0.1.0.dist-info/top_level.txt
zelphi-0.1.0.dist-info/RECORD
