Metadata-Version: 2.4
Name: zelphi
Version: 0.1.0
Summary: A short description of the Zelphi utility package.
Author-email: Gokulakrishnan M <hello@gokulakrishnan.in>
License: MIT License
Project-URL: Homepage, https://github.com/gokul-a-krishnan/zelphi-python
Project-URL: Issues, https://github.com/gokul-a-krishnan/zelphi-python/issues
Project-URL: Repository, https://github.com/gokul-a-krishnan/zelphi-python
Requires-Python: >=3.8
